{
  "Tamiya XF (Acrílicos Mate)": [
    {"id": "XF-1", "nombre": "Flat Black", "hex": "#2B2B2B"},
    {"id": "XF-2", "nombre": "Flat White", "hex": "#F0F0F0"},
    {"id": "XF-3", "nombre": "Flat Yellow", "hex": "#F7D94A"},
    {"id": "XF-4", "nombre": "Yellow Green", "hex": "#7BA05B"},
    {"id": "XF-5", "nombre": "Flat Green", "hex": "#4A7043"},
    {"id": "XF-6", "nombre": "Copper", "hex": "#B87333"},
    {"id": "XF-7", "nombre": "Flat Red", "hex": "#B22222"},
    {"id": "XF-8", "nombre": "Flat Blue", "hex": "#4682B4"},
    {"id": "XF-9", "nombre": "Hull Red", "hex": "#6B2C2C"},
    {"id": "XF-10", "nombre": "Flat Brown", "hex": "#5C4033"},
    {"id": "XF-11", "nombre": "JN Green", "hex": "#355E3B"},
    {"id": "XF-12", "nombre": "JN Grey", "hex": "#A9A9A9"},
    {"id": "XF-13", "nombre": "JA Green", "hex": "#4A7043"},
    {"id": "XF-14", "nombre": "JA Grey", "hex": "#B0C4DE"},
    {"id": "XF-15", "nombre": "Flat Flesh", "hex": "#E4C8A8"},
    {"id": "XF-16", "nombre": "Flat Aluminum", "hex": "#C0C0C0"},
    {"id": "XF-17", "nombre": "Sea Blue", "hex": "#2F4F4F"},
    {"id": "XF-18", "nombre": "Medium Blue", "hex": "#5A7D9A"},
    {"id": "XF-19", "nombre": "Sky Grey", "hex": "#B0C4DE"},
    {"id": "XF-20", "nombre": "Medium Grey", "hex": "#808080"},
    {"id": "XF-21", "nombre": "Sky", "hex": "#87CEEB"},
    {"id": "XF-22", "nombre": "RLM Grey", "hex": "#A9A9A9"},
    {"id": "XF-23", "nombre": "Light Blue", "hex": "#ADD8E6"},
    {"id": "XF-24", "nombre": "Dark Grey", "hex": "#4D4D4D"},
    {"id": "XF-25", "nombre": "Light Sea Grey", "hex": "#778899"},
    {"id": "XF-26", "nombre": "Deep Green", "hex": "#006400"},
    {"id": "XF-27", "nombre": "Black Green", "hex": "#1C2526"},
    {"id": "XF-49", "nombre": "Khaki", "hex": "#C3B091"},
    {"id": "XF-50", "nombre": "Field Blue", "hex": "#4A708B"},
    {"id": "XF-51", "nombre": "Khaki Drab", "hex": "#6B8E23"},
    {"id": "XF-52", "nombre": "Flat Earth", "hex": "#8B7355"},
    {"id": "XF-53", "nombre": "Neutral Grey", "hex": "#808080"},
    {"id": "XF-54", "nombre": "Dark Sea Grey", "hex": "#5C6673"},
    {"id": "XF-55", "nombre": "Deck Tan", "hex": "#D2B48C"},
    {"id": "XF-56", "nombre": "Metallic Grey", "hex": "#A9A9A9"},
    {"id": "XF-57", "nombre": "Buff", "hex": "#D2B48C"},
    {"id": "XF-58", "nombre": "Olive Green", "hex": "#556B2F"},
    {"id": "XF-59", "nombre": "Desert Yellow", "hex": "#EDC9AF"},
    {"id": "XF-60", "nombre": "Dark Yellow", "hex": "#DAA520"},
    {"id": "XF-61", "nombre": "Dark Green", "hex": "#355E3B"},
    {"id": "XF-62", "nombre": "Olive Drab", "hex": "#6B8E23"},
    {"id": "XF-63", "nombre": "German Grey", "hex": "#5C5C5C"},
    {"id": "XF-64", "nombre": "Red Brown", "hex": "#8B4513"},
    {"id": "XF-65", "nombre": "Field Grey", "hex": "#5F9EA0"},
    {"id": "XF-66", "nombre": "Light Grey", "hex": "#D3D3D3"},
    {"id": "XF-67", "nombre": "NATO Olive", "hex": "#556B2F"},
    {"id": "XF-68", "nombre": "NATO Brown", "hex": "#8B4513"},
    {"id": "XF-69", "nombre": "NATO Black", "hex": "#2F4F4F"}
  ],

  "Tamiya X (Acrílicos Brillantes)": [
    {"id": "X-1", "nombre": "Black", "hex": "#000000"},
    {"id": "X-2", "nombre": "White", "hex": "#FFFFFF"},
    {"id": "X-3", "nombre": "Royal Blue", "hex": "#4169E1"},
    {"id": "X-4", "nombre": "Blue", "hex": "#0000FF"},
    {"id": "X-5", "nombre": "Green", "hex": "#008000"},
    {"id": "X-6", "nombre": "Orange", "hex": "#FFA500"},
    {"id": "X-7", "nombre": "Red", "hex": "#FF0000"},
    {"id": "X-8", "nombre": "Lemon Yellow", "hex": "#FFFF00"},
    {"id": "X-9", "nombre": "Brown", "hex": "#A52A2A"},
    {"id": "X-10", "nombre": "Gun Metal", "hex": "#2A3439"},
    {"id": "X-11", "nombre": "Chrome Silver", "hex": "#B0C4DE"},
    {"id": "X-12", "nombre": "Gold Leaf", "hex": "#FFD700"},
    {"id": "X-13", "nombre": "Copper", "hex": "#B87333"},
    {"id": "X-14", "nombre": "Sky Blue", "hex": "#87CEEB"},
    {"id": "X-15", "nombre": "Light Green", "hex": "#90EE90"},
    {"id": "X-16", "nombre": "Purple", "hex": "#800080"},
    {"id": "X-17", "nombre": "Pink", "hex": "#FFC0CB"},
    {"id": "X-18", "nombre": "Semi Gloss Black", "hex": "#1C1C1C"},
    {"id": "X-19", "nombre": "Smoke", "hex": "#708090"},
    {"id": "X-22", "nombre": "Clear", "hex": "#FFFFFF"}
  ],

  "Tamiya LP (Lacquer Paint)": [
    {"id": "LP-1", "nombre": "Black", "acabado": "Gloss"},
    {"id": "LP-2", "nombre": "White", "acabado": "Gloss"},
    {"id": "LP-3", "nombre": "Flat Black", "acabado": "Flat"},
    {"id": "LP-4", "nombre": "Flat White", "acabado": "Flat"},
    {"id": "LP-5", "nombre": "Semi Gloss Black", "acabado": "Semi Gloss"},
    {"id": "LP-6", "nombre": "Pure Blue", "acabado": "Gloss"},
    {"id": "LP-7", "nombre": "Pure Red", "acabado": "Gloss"},
    {"id": "LP-8", "nombre": "Pure Yellow", "acabado": "Gloss"},
    {"id": "LP-9", "nombre": "Clear", "acabado": "Gloss"},
    {"id": "LP-10", "nombre": "Lacquer Thinner", "acabado": "Thinner (no color)"},
    {"id": "LP-11", "nombre": "Silver", "acabado": "Metallic Gloss"},
    {"id": "LP-12", "nombre": "IJN Gray Kure Arsenal", "acabado": "Flat"},
    {"id": "LP-13", "nombre": "IJN Gray Sasebo Arsenal", "acabado": "Flat"},
    {"id": "LP-14", "nombre": "IJN Gray Maizuru Arsenal", "acabado": "Flat"},
    {"id": "LP-15", "nombre": "IJN Gray Yokosuka Arsenal", "acabado": "Flat"},
    {"id": "LP-16", "nombre": "Wooden Deck Tan", "acabado": "Flat"},
    {"id": "LP-17", "nombre": "Linoleum Deck Brown", "acabado": "Flat"},
    {"id": "LP-18", "nombre": "Dull Red", "acabado": "Flat"},
    {"id": "LP-19", "nombre": "Gun Metal", "acabado": "Gloss"},
    {"id": "LP-20", "nombre": "Light Gun Metal", "acabado": "Gloss"},
    {"id": "LP-21", "nombre": "Italian Red", "acabado": "Gloss"},
    {"id": "LP-22", "nombre": "Flat Base", "acabado": "Additive"},
    {"id": "LP-23", "nombre": "Flat Clear", "acabado": "Flat"},
    {"id": "LP-24", "nombre": "Semi Gloss Clear", "acabado": "Semi Gloss"},
    {"id": "LP-25", "nombre": "Brown (JGSDF)", "acabado": "Flat"},
    {"id": "LP-26", "nombre": "Dark Green (JGSDF)", "acabado": "Flat"},
    {"id": "LP-27", "nombre": "German Gray", "acabado": "Flat"},
    {"id": "LP-28", "nombre": "Olive Drab", "acabado": "Flat"},
    {"id": "LP-29", "nombre": "Olive Drab 2", "acabado": "Flat"},
    {"id": "LP-30", "nombre": "Light Sand", "acabado": "Flat"},
    {"id": "LP-31", "nombre": "Dark Green 2 IJN", "acabado": "Semi Gloss"},
    {"id": "LP-32", "nombre": "Light Gray IJN", "acabado": "Semi Gloss"},
    {"id": "LP-33", "nombre": "Gray Green IJN", "acabado": "Semi Gloss"},
    {"id": "LP-34", "nombre": "Light Gray", "acabado": "Flat"},
    {"id": "LP-35", "nombre": "Insignia White", "acabado": "Flat"},
    {"id": "LP-36", "nombre": "Dark Ghost Gray", "acabado": "Flat"},
    {"id": "LP-37", "nombre": "Light Ghost Gray", "acabado": "Flat"},
    {"id": "LP-38", "nombre": "Flat Aluminum", "acabado": "Metallic Flat"},
    {"id": "LP-39", "nombre": "Racing White", "acabado": "Gloss"},
    {"id": "LP-40", "nombre": "Metallic Black", "acabado": "Gloss"},
    {"id": "LP-41", "nombre": "Mica Blue", "acabado": "Gloss"},
    {"id": "LP-42", "nombre": "Mica Red", "acabado": "Gloss"},
    {"id": "LP-43", "nombre": "Pearl White", "acabado": "Gloss"},
    {"id": "LP-44", "nombre": "Metallic Orange", "acabado": "Gloss"},
    {"id": "LP-45", "nombre": "Racing Blue", "acabado": "Gloss"},
    {"id": "LP-46", "nombre": "Pure Metallic Red", "acabado": "Gloss"},
    {"id": "LP-47", "nombre": "Pearl Blue", "acabado": "Gloss"},
    {"id": "LP-48", "nombre": "Sparkling Silver", "acabado": "Metallic Gloss"},
    {"id": "LP-49", "nombre": "Pearl Clear", "acabado": "Gloss"},
    {"id": "LP-50", "nombre": "Bright Red", "acabado": "Gloss"},
    {"id": "LP-51", "nombre": "Pure Orange", "acabado": "Gloss"},
    {"id": "LP-52", "nombre": "Clear Red", "acabado": "Gloss"},
    {"id": "LP-53", "nombre": "Clear Orange", "acabado": "Gloss"},
    {"id": "LP-54", "nombre": "Dark Iron", "acabado": "Flat"},
    {"id": "LP-55", "nombre": "Dark Yellow 2", "acabado": "Flat"},
    {"id": "LP-56", "nombre": "Dark Green 2", "acabado": "Flat"},
    {"id": "LP-57", "nombre": "Red Brown 2", "acabado": "Flat"},
    {"id": "LP-58", "nombre": "NATO Green", "acabado": "Flat"},
    {"id": "LP-59", "nombre": "NATO Brown", "acabado": "Flat"},
    {"id": "LP-60", "nombre": "NATO Black", "acabado": "Flat"},
    {"id": "LP-61", "nombre": "Metallic Gray", "acabado": "Metallic Flat"},
    {"id": "LP-62", "nombre": "Titanium Gold", "acabado": "Metallic Gloss"},
    {"id": "LP-63", "nombre": "Titanium Silver", "acabado": "Metallic Gloss"},
    {"id": "LP-64", "nombre": "Olive Drab (JGSDF)", "acabado": "Flat"},
    {"id": "LP-65", "nombre": "Rubber Black", "acabado": "Flat"},
    {"id": "LP-66", "nombre": "Flat Flesh", "acabado": "Flat"},
    {"id": "LP-67", "nombre": "Smoke", "acabado": "Gloss"},
    {"id": "LP-68", "nombre": "Clear Blue", "acabado": "Gloss"},
    {"id": "LP-69", "nombre": "Clear Yellow", "acabado": "Gloss"},
    {"id": "LP-70", "nombre": "Gloss Aluminum", "acabado": "Gloss"},
    {"id": "LP-71", "nombre": "Champagne Gold", "acabado": "Gloss"},
    {"id": "LP-72", "nombre": "Mica Silver", "acabado": "Gloss"},
    {"id": "LP-73", "nombre": "Khaki", "acabado": "Flat"},
    {"id": "LP-74", "nombre": "Flat Earth", "acabado": "Flat"},
    {"id": "LP-75", "nombre": "Buff", "acabado": "Flat"},
    {"id": "LP-76", "nombre": "Yellow-Brown (DAK 1941)", "acabado": "Flat"},
    {"id": "LP-77", "nombre": "Light Brown (DAK 1942)", "acabado": "Flat"},
    {"id": "LP-78", "nombre": "Flat Blue", "acabado": "Flat"},
    {"id": "LP-79", "nombre": "Flat Red", "acabado": "Flat"},
    {"id": "LP-80", "nombre": "Flat Yellow", "acabado": "Flat"},
    {"id": "LP-81", "nombre": "Mixing Blue", "acabado": "Gloss"},
    {"id": "LP-82", "nombre": "Mixing Red", "acabado": "Gloss"},
    {"id": "LP-83", "nombre": "Mixing Yellow", "acabado": "Gloss"},
    {"id": "LP-84", "nombre": "Camouflage Gray", "acabado": "Flat"},
    {"id": "LP-85", "nombre": "Medium Air Gray", "acabado": "Flat"}
  ] 

  "Tamiya TS (Spray Paint)": [
    {"id": "TS-1", "nombre": "Red", "acabado": "Gloss"},
    {"id": "TS-2", "nombre": "Dark Green", "acabado": "Gloss"},
    {"id": "TS-3", "nombre": "Dark Yellow", "acabado": "Gloss"},
    {"id": "TS-4", "nombre": "German Gray", "acabado": "Matte"},
    {"id": "TS-5", "nombre": "Olive Drab", "acabado": "Matte"},
    {"id": "TS-6", "nombre": "Matte Black", "acabado": "Matte"},
    {"id": "TS-7", "nombre": "Racing White", "acabado": "Gloss"},
    {"id": "TS-8", "nombre": "Italian Red", "acabado": "Gloss"},
    {"id": "TS-13", "nombre": "Clear", "acabado": "Gloss"},
    {"id": "TS-14", "nombre": "Black", "acabado": "Gloss"},
    {"id": "TS-16", "nombre": "Yellow", "acabado": "Gloss"},
    {"id": "TS-17", "nombre": "Aluminum Silver", "acabado": "Metallic"},
    {"id": "TS-26", "nombre": "Pure White", "acabado": "Gloss"},
    {"id": "TS-27", "nombre": "Matte White", "acabado": "Matte"},
    {"id": "TS-29", "nombre": "Semi Gloss Black", "acabado": "Semi Gloss"},
    {"id": "TS-30", "nombre": "Silver", "acabado": "Metallic"},
    {"id": "TS-33", "nombre": "Dull Red", "acabado": "Matte"},
    {"id": "TS-38", "nombre": "Gun Metal", "acabado": "Metallic"},
    {"id": "TS-39", "nombre": "Mica Red", "acabado": "Pearl/Metallic"},
    {"id": "TS-40", "nombre": "Metallic Black", "acabado": "Metallic"},
    {"id": "TS-42", "nombre": "Light Gun Metal", "acabado": "Metallic"},
    {"id": "TS-45", "nombre": "Pearl White", "acabado": "Pearl"},
    {"id": "TS-46", "nombre": "Light Sand", "acabado": "Matte"},
    {"id": "TS-49", "nombre": "Bright Red", "acabado": "Gloss"},
    {"id": "TS-50", "nombre": "Mica Blue", "acabado": "Pearl/Metallic"},
    {"id": "TS-51", "nombre": "Racing Blue", "acabado": "Gloss"},
    {"id": "TS-61", "nombre": "NATO Green", "acabado": "Matte"},
    {"id": "TS-62", "nombre": "NATO Brown", "acabado": "Matte"},
    {"id": "TS-63", "nombre": "NATO Black", "acabado": "Matte"},
    {"id": "TS-64", "nombre": "Dark Mica Blue", "acabado": "Pearl/Metallic"},
    {"id": "TS-65", "nombre": "Pearl Clear", "acabado": "Pearl"},
    {"id": "TS-66", "nombre": "IJN Gray (Kure)", "acabado": "Matte"},
    {"id": "TS-67", "nombre": "IJN Gray (Sasebo)", "acabado": "Matte"},
    {"id": "TS-68", "nombre": "Wooden Deck Tan", "acabado": "Matte"},
    {"id": "TS-69", "nombre": "Linoleum Deck Brown", "acabado": "Matte"},
    {"id": "TS-71", "nombre": "Smoke", "acabado": "Gloss"},
    {"id": "TS-72", "nombre": "Clear Blue", "acabado": "Gloss"},
    {"id": "TS-73", "nombre": "Clear Orange", "acabado": "Gloss"},
    {"id": "TS-74", "nombre": "Clear Red", "acabado": "Gloss"},
    {"id": "TS-75", "nombre": "Champagne Gold", "acabado": "Metallic"},
    {"id": "TS-76", "nombre": "Mica Silver", "acabado": "Pearl/Metallic"},
    {"id": "TS-80", "nombre": "Flat Clear", "acabado": "Flat"},
    {"id": "TS-83", "nombre": "Metallic Silver", "acabado": "Metallic"},
    {"id": "TS-86", "nombre": "Pure Red", "acabado": "Gloss"},
    {"id": "TS-87", "nombre": "Titanium Gold", "acabado": "Metallic"},
    {"id": "TS-88", "nombre": "Titanium Silver", "acabado": "Metallic"},
    {"id": "TS-89", "nombre": "Pearl Blue", "acabado": "Pearl"},
    {"id": "TS-90", "nombre": "Brown (JGSDF)", "acabado": "Matte"},
    {"id": "TS-91", "nombre": "Dark Green (JGSDF)", "acabado": "Matte"},
    {"id": "TS-92", "nombre": "Metallic Orange", "acabado": "Metallic"},
    {"id": "TS-93", "nombre": "Pure Blue", "acabado": "Gloss"},
    {"id": "TS-95", "nombre": "Pure Metallic Red", "acabado": "Metallic"},
    {"id": "TS-98", "nombre": "Pure Orange", "acabado": "Gloss"},
    {"id": "TS-99", "nombre": "IJN Gray (Maizuru)", "acabado": "Matte"},
    {"id": "TS-100", "nombre": "Semi-Gloss Bright Gun Metal", "acabado": "Semi Gloss Metallic"},
    {"id": "TS-101", "nombre": "Base White", "acabado": "Gloss"},
    {"id": "TS-102", "nombre": "Cobalt Green", "acabado": "Gloss"}
  ]

  "Mr.Color (Gunze Sangyo)": [
    {"id": "C1", "nombre": "Gloss White", "hex": "#FFFFFF"},
    {"id": "C2", "nombre": "Gloss Black", "hex": "#000000"},
    {"id": "C3", "nombre": "Gloss Red", "hex": "#FF0000"},
    {"id": "C4", "nombre": "Yellow", "hex": "#FFFF00"},
    {"id": "C5", "nombre": "Blue", "hex": "#0000FF"},
    {"id": "C6", "nombre": "Green", "hex": "#008000"},
    {"id": "C7", "nombre": "Gloss Green", "hex": "#00FF00"},
    {"id": "C8", "nombre": "Silver", "hex": "#C0C0C0"},
    {"id": "C10", "nombre": "Gunship Grey", "hex": "#778899"},
    {"id": "C11", "nombre": "Light Gull Grey", "hex": "#D3D3D3"},
    {"id": "C13", "nombre": "Navy Blue", "hex": "#000080"},
    {"id": "C14", "nombre": "Olive Green", "hex": "#556B2F"},
    {"id": "C15", "nombre": "IJN Green", "hex": "#355E3B"},
    {"id": "C33", "nombre": "Dark Sea Grey", "hex": "#5C6673"},
    {"id": "C34", "nombre": "Sky", "hex": "#87CEEB"},
    {"id": "C35", "nombre": "IJN Grey", "hex": "#A9A9A9"},
    {"id": "C36", "nombre": "Haze Grey", "hex": "#A9A9A9"},
    {"id": "C37", "nombre": "Grey Violet", "hex": "#8A2BE2"},
    {"id": "C46", "nombre": "Clear Red", "hex": "#FF4040"},
    {"id": "C62", "nombre": "Insignia White", "hex": "#F5F5F5"},
    {"id": "C66", "nombre": "Bright Green", "hex": "#00FF7F"},
    {"id": "C69", "nombre": "Off White", "hex": "#F5F5F5"},
    {"id": "C77", "nombre": "Tire Black", "hex": "#1C1C1C"},
    {"id": "C84", "nombre": "Titanium Gold", "hex": "#D4AF37"},
    {"id": "C91", "nombre": "Clear Red", "hex": "#FF4040"},
    {"id": "C92", "nombre": "Semi Gloss Black", "hex": "#2F4F4F"},
    {"id": "C128", "nombre": "Grayish Green", "hex": "#8FBC8F"},
    {"id": "C304", "nombre": "Olive Drab", "hex": "#6B8E23"},
    {"id": "C306", "nombre": "FS Grey", "hex": "#808080"},
    {"id": "C317", "nombre": "FS Grey", "hex": "#A9A9A9"},
    {"id": "C324", "nombre": "Dark Green", "hex": "#006400"},
    {"id": "C329", "nombre": "Blue Angels Yellow", "hex": "#FFD700"},
    {"id": "C331", "nombre": "Dark Sea Grey", "hex": "#5C6673"},
    {"id": "C335", "nombre": "Medium Sea Grey", "hex": "#8A9A9A"},
    {"id": "C337", "nombre": "FS Grey", "hex": "#B0C4DE"},
    {"id": "C338", "nombre": "Light Aircraft Grey", "hex": "#D3D3D3"},
    {"id": "C339", "nombre": "FS Dark Ghost Grey", "hex": "#778899"},
    {"id": "C340", "nombre": "FS Engine Grey", "hex": "#4D4D4D"}
  ],

  "Humbrol Enamel / Acrylic": [
    {"id": "1", "nombre": "Grey Primer", "hex": "#808080"},
    {"id": "2", "nombre": "Emerald", "hex": "#50C878"},
    {"id": "3", "nombre": "Brunswick Green", "hex": "#1B4D3E"},
    {"id": "7", "nombre": "Light Buff", "hex": "#F0E68C"},
    {"id": "9", "nombre": "Tan", "hex": "#D2B48C"},
    {"id": "11", "nombre": "Silver", "hex": "#C0C0C0"},
    {"id": "14", "nombre": "French Blue", "hex": "#007FFF"},
    {"id": "15", "nombre": "Midnight Blue", "hex": "#191970"},
    {"id": "16", "nombre": "Gold", "hex": "#FFD700"},
    {"id": "18", "nombre": "Orange", "hex": "#FFA500"},
    {"id": "19", "nombre": "Bright Red", "hex": "#FF0000"},
    {"id": "21", "nombre": "Black", "hex": "#000000"},
    {"id": "22", "nombre": "White", "hex": "#FFFFFF"},
    {"id": "23", "nombre": "Duck Egg Blue", "hex": "#D1F0E0"},
    {"id": "24", "nombre": "Trainer Yellow", "hex": "#FFFF00"},
    {"id": "25", "nombre": "Blue", "hex": "#0000FF"},
    {"id": "26", "nombre": "Khaki", "hex": "#C3B091"},
    {"id": "27", "nombre": "Sea Grey", "hex": "#778899"},
    {"id": "28", "nombre": "Camouflage Grey", "hex": "#8A9A9A"},
    {"id": "29", "nombre": "Dark Earth", "hex": "#8B7355"},
    {"id": "30", "nombre": "Dark Green", "hex": "#006400"},
    {"id": "33", "nombre": "Black", "hex": "#000000"},
    {"id": "34", "nombre": "White", "hex": "#FFFFFF"},
    {"id": "53", "nombre": "Gunmetal", "hex": "#2A3439"},
    {"id": "56", "nombre": "Aluminium", "hex": "#D3D3D3"},
    {"id": "61", "nombre": "Flesh", "hex": "#E4C8A8"},
    {"id": "62", "nombre": "Leather", "hex": "#8B4513"},
    {"id": "64", "nombre": "Light Grey", "hex": "#D3D3D3"},
    {"id": "65", "nombre": "Aircraft Blue", "hex": "#5F9EA0"},
    {"id": "78", "nombre": "Cockpit Green", "hex": "#556B2F"},
    {"id": "93", "nombre": "Desert Yellow", "hex": "#EDC9AF"},
    {"id": "96", "nombre": "RAF Blue", "hex": "#2F4F7F"},
    {"id": "102", "nombre": "Cream", "hex": "#FFFDD0"},
    {"id": "140", "nombre": "Gull Grey", "hex": "#B0C4DE"}
  ],

  "RAL Colours (RAL Classic)": [
    {"id": "RAL 1000", "nombre": "Green beige", "hex": "#CDBA88"},
    {"id": "RAL 1001", "nombre": "Beige", "hex": "#D1B894"},
    {"id": "RAL 1002", "nombre": "Sand yellow", "hex": "#D9B35F"},
    {"id": "RAL 1003", "nombre": "Signal yellow", "hex": "#F9A800"},
    {"id": "RAL 1004", "nombre": "Golden yellow", "hex": "#E49E3E"},
    {"id": "RAL 1005", "nombre": "Honey yellow", "hex": "#D6893A"},
    {"id": "RAL 1006", "nombre": "Maize yellow", "hex": "#E1A627"},
    {"id": "RAL 1007", "nombre": "Daffodil yellow", "hex": "#E79E00"},
    {"id": "RAL 1011", "nombre": "Brown beige", "hex": "#AF804F"},
    {"id": "RAL 1012", "nombre": "Lemon yellow", "hex": "#F7E000"},
    {"id": "RAL 1013", "nombre": "Oyster white", "hex": "#E3D9C9"},
    {"id": "RAL 1014", "nombre": "Ivory", "hex": "#E4D7C5"},
    {"id": "RAL 1015", "nombre": "Light ivory", "hex": "#F1E3D0"},
    {"id": "RAL 1016", "nombre": "Sulphur yellow", "hex": "#F1E000"},
    {"id": "RAL 1017", "nombre": "Saffron yellow", "hex": "#F4A32C"},
    {"id": "RAL 1018", "nombre": "Zinc yellow", "hex": "#F3E03E"},
    {"id": "RAL 1019", "nombre": "Grey beige", "hex": "#A9A491"},
    {"id": "RAL 1020", "nombre": "Olive yellow", "hex": "#9D8F6E"},
    {"id": "RAL 1021", "nombre": "Rape yellow", "hex": "#F3D03E"},
    {"id": "RAL 1023", "nombre": "Traffic yellow", "hex": "#F4C300"},
    {"id": "RAL 1024", "nombre": "Ochre yellow", "hex": "#E6B71C"},
    {"id": "RAL 2000", "nombre": "Yellow orange", "hex": "#F15A22"},
    {"id": "RAL 3000", "nombre": "Flame red", "hex": "#AF2A2F"},
    {"id": "RAL 4001", "nombre": "Red lilac", "hex": "#D39ECB"},
    {"id": "RAL 5000", "nombre": "Violet blue", "hex": "#354E6B"},
    {"id": "RAL 6000", "nombre": "Patina green", "hex": "#316650"},
    {"id": "RAL 7000", "nombre": "Squirrel grey", "hex": "#7A888E"},
    {"id": "RAL 8000", "nombre": "Green brown", "hex": "#8A6642"},
    {"id": "RAL 9000", "nombre": "White aluminium", "hex": "#F0F0F0"}
  ],

  "Pantone Solid Coated (PMS C)": [
    {"id": "Pantone Yellow", "nombre": "Pantone Yellow", "hex": "#FFE800"},
    {"id": "100 C", "nombre": "Pantone 100 C", "hex": "#F6EB61"},
    {"id": "101 C", "nombre": "Pantone 101 C", "hex": "#F3E000"},
    {"id": "102 C", "nombre": "Pantone 102 C", "hex": "#F0D500"},
    {"id": "103 C", "nombre": "Pantone 103 C", "hex": "#C5A900"},
    {"id": "104 C", "nombre": "Pantone 104 C", "hex": "#AF9800"},
    {"id": "105 C", "nombre": "Pantone 105 C", "hex": "#897A27"},
    {"id": "106 C", "nombre": "Pantone 106 C", "hex": "#F9E814"},
    {"id": "107 C", "nombre": "Pantone 107 C", "hex": "#F7E300"},
    {"id": "108 C", "nombre": "Pantone 108 C", "hex": "#F5D700"},
    {"id": "109 C", "nombre": "Pantone 109 C", "hex": "#F2CA00"},
    {"id": "110 C", "nombre": "Pantone 110 C", "hex": "#D9B600"},
    {"id": "111 C", "nombre": "Pantone 111 C", "hex": "#B89F00"},
    {"id": "112 C", "nombre": "Pantone 112 C", "hex": "#9C8A00"},
    {"id": "113 C", "nombre": "Pantone 113 C", "hex": "#F5E050"},
    {"id": "114 C", "nombre": "Pantone 114 C", "hex": "#F2D93E"},
    {"id": "115 C", "nombre": "Pantone 115 C", "hex": "#F0D32C"},
    {"id": "116 C", "nombre": "Pantone 116 C", "hex": "#EDCC00"},
    {"id": "117 C", "nombre": "Pantone 117 C", "hex": "#D4B200"},
    {"id": "118 C", "nombre": "Pantone 118 C", "hex": "#B89A00"},
    {"id": "119 C", "nombre": "Pantone 119 C", "hex": "#9C8500"},
    {"id": "120 C", "nombre": "Pantone 120 C", "hex": "#F2E0B2"},
    {"id": "121 C", "nombre": "Pantone 121 C", "hex": "#F0D99E"},
    {"id": "122 C", "nombre": "Pantone 122 C", "hex": "#EDC88C"},
    {"id": "123 C", "nombre": "Pantone 123 C", "hex": "#EAB76A"},
    {"id": "124 C", "nombre": "Pantone 124 C", "hex": "#E0A347"},
    {"id": "125 C", "nombre": "Pantone 125 C", "hex": "#C68C2E"},
    {"id": "126 C", "nombre": "Pantone 126 C", "hex": "#A8751C"},
    {"id": "Orange 021 C", "nombre": "Pantone Orange 021 C", "hex": "#FF5F00"},
    {"id": "Warm Red C", "nombre": "Pantone Warm Red C", "hex": "#F9423A"},
    {"id": "Red 032 C", "nombre": "Pantone Red 032 C", "hex": "#EF3340"},
    {"id": "179 C", "nombre": "Pantone 179 C", "hex": "#E74C3C"},
    {"id": "180 C", "nombre": "Pantone 180 C", "hex": "#C0392B"},
    {"id": "181 C", "nombre": "Pantone 181 C", "hex": "#96281B"},
    {"id": "185 C", "nombre": "Pantone 185 C", "hex": "#E3120C"},
    {"id": "186 C", "nombre": "Pantone 186 C", "hex": "#C8102E"},
    {"id": "187 C", "nombre": "Pantone 187 C", "hex": "#A6192E"},
    {"id": "199 C", "nombre": "Pantone 199 C", "hex": "#D50032"},
    {"id": "200 C", "nombre": "Pantone 200 C", "hex": "#B10333"},
    {"id": "201 C", "nombre": "Pantone 201 C", "hex": "#9E0031"},
    {"id": "202 C", "nombre": "Pantone 202 C", "hex": "#8A002E"},
    {"id": "Reflex Blue C", "nombre": "Pantone Reflex Blue C", "hex": "#001489"},
    {"id": "280 C", "nombre": "Pantone 280 C", "hex": "#012169"},
    {"id": "281 C", "nombre": "Pantone 281 C", "hex": "#00205B"},
    {"id": "285 C", "nombre": "Pantone 285 C", "hex": "#0072CE"},
    {"id": "286 C", "nombre": "Pantone 286 C", "hex": "#0033A0"},
    {"id": "287 C", "nombre": "Pantone 287 C", "hex": "#003087"},
    {"id": "288 C", "nombre": "Pantone 288 C", "hex": "#002F6C"},
    {"id": "293 C", "nombre": "Pantone 293 C", "hex": "#003DA5"},
    {"id": "300 C", "nombre": "Pantone 300 C", "hex": "#0067A0"},
    {"id": "Process Blue C", "nombre": "Pantone Process Blue C", "hex": "#0085CA"},
    {"id": "Green C", "nombre": "Pantone Green C", "hex": "#00A859"},
    {"id": "327 C", "nombre": "Pantone 327 C", "hex": "#007A33"},
    {"id": "348 C", "nombre": "Pantone 348 C", "hex": "#00543D"},
    {"id": "Black C", "nombre": "Pantone Black C", "hex": "#101820"},
    {"id": "Cool Gray 11 C", "nombre": "Pantone Cool Gray 11 C", "hex": "#63666A"},
    {"id": "877 C", "nombre": "Pantone 877 C (Metallic Silver)", "hex": "#8A8D91"}
  ]
}
